apoactor/__init__.py
apoactor/__main__.py
apoactor/actor/__init__.py
apoactor/actor/actor.py
apoactor/actor/commands/__init__.py
apoactor/actor/commands/status.py
apoactor/dataclasses.py
apoactor/etc/apoactor.yml
apoactor/etc/schema.json
apoactor/tool.py
apoactor/tpm.py
apoactor/wx.py
sdss_apoactor-4.1.0.dist-info/LICENSE.md
sdss_apoactor-4.1.0.dist-info/METADATA
sdss_apoactor-4.1.0.dist-info/WHEEL
sdss_apoactor-4.1.0.dist-info/entry_points.txt
sdss_apoactor-4.1.0.dist-info/RECORD
